franciscomalo_actividad4/__init__.py
franciscomalo_actividad4-1.0.dist-info/LICENSE
franciscomalo_actividad4-1.0.dist-info/METADATA
franciscomalo_actividad4-1.0.dist-info/WHEEL
franciscomalo_actividad4-1.0.dist-info/top_level.txt
franciscomalo_actividad4-1.0.dist-info/RECORD
