Metadata-Version: 2.1
Name: franciscomalo-actividad4
Version: 1.0
Summary: A tool to tell the prime numbers up to a given number.
Home-page: UNKNOWN
Author: Francisco Malo
Author-email: fmalourarte@gmail.com
License: GNU GPLv3
Keywords: prime numbers
Platform: UNKNOWN
Classifier: Development Status :: 4 - Beta
Classifier: Intended Audience :: Developers
Classifier: Topic :: Utilities
Classifier: License :: OSI Approved :: GNU General Public License v3 (GPLv3)
Classifier: Programming Language :: Python :: 3
Classifier: Operating System :: OS Independent
